MANIFEST.in
README.txt
setup.py
docs/COPYRIGHT.txt
docs/HISTORY.txt
docs/LICENSE.txt
src/cromlech/__init__.py
src/cromlech.sessions.file.egg-info/PKG-INFO
src/cromlech.sessions.file.egg-info/SOURCES.txt
src/cromlech.sessions.file.egg-info/dependency_links.txt
src/cromlech.sessions.file.egg-info/namespace_packages.txt
src/cromlech.sessions.file.egg-info/not-zip-safe
src/cromlech.sessions.file.egg-info/requires.txt
src/cromlech.sessions.file.egg-info/top_level.txt
src/cromlech/sessions/__init__.py
src/cromlech/sessions/file/__init__.py
src/cromlech/sessions/file/store.py
src/cromlech/sessions/file/utils.py
src/cromlech/sessions/file/tests/test_session.txt